pulsar.py
pulsar/__init__.py
pulsar/pulsar.py
pulsar/lib/libpulsar.so
pulsar_python-1.0.1.dist-info/licenses/LICENSE
pulsar_python-1.0.1.dist-info/METADATA
pulsar_python-1.0.1.dist-info/WHEEL
pulsar_python-1.0.1.dist-info/top_level.txt
pulsar_python-1.0.1.dist-info/RECORD
