Metadata-Version: 2.4
Name: pulsar-python
Version: 1.0.1
Summary: Python wrapper for Pulsar web server
Home-page: https://github.com/abiiranathan/pulsar/tree/main/python
Author: Dr. Abiira Nathan
Author-email: nabiira2by2@gmail.com
License: MIT
Project-URL: Bug Reports, https://github.com/abiiranathan/pulsar/issues
Project-URL: Source, https://github.com/abiiranathan/pulsar/tree/main/python
Keywords: web server http framework
Classifier: Development Status :: 4 - Beta
Classifier: Intended Audience :: Developers
Classifier: License :: OSI Approved :: MIT License
Classifier: Programming Language :: Python :: 3.8
Classifier: Programming Language :: Python :: 3.9
Classifier: Programming Language :: Python :: 3.10
Classifier: Programming Language :: Python :: 3.11
Classifier: Programming Language :: Python :: 3.12
Classifier: Programming Language :: Python :: 3.13
Classifier: Operating System :: POSIX :: Linux
Classifier: Operating System :: MacOS :: MacOS X
Classifier: Topic :: Internet :: WWW/HTTP :: HTTP Servers
Requires-Python: >=3.8
License-File: LICENSE
Dynamic: author
Dynamic: author-email
Dynamic: classifier
Dynamic: description
Dynamic: description-content-type
Dynamic: home-page
Dynamic: keywords
Dynamic: license
Dynamic: license-file
Dynamic: project-url
Dynamic: requires-python
Dynamic: summary
